{
  "type": "FeatureCollection",
  "features": [
    {
      "type": "Feature",
      "id": "psa_station_1",
      "geometry": {
        "type": "Point",
        "coordinates": [
          -73.82677717928686,
          40.85929320319798
        ]
      },
      "properties": {
        "name": "Co-Op City",
        "project": "Penn Station Access (MTA Metro-North)",
        "status": "under construction",
        "line": "New Haven Line (via Amtrak Hell Gate Line)",
        "borough": "Bronx",
        "neighborhood": "Co-op City, Bronx",
        "source_note": "Coords from station Wikipedia pages; station set from MTA project page",
        "created_at_utc": "2025-10-20T23:43:53Z",
        "crs_note": "EPSG:4326 (WGS84 lon,lat)"
      }
    },
    {
      "type": "Feature",
      "id": "psa_station_2",
      "geometry": {
        "type": "Point",
        "coordinates": [
          -73.84323218520936,
          40.85069594171735
        ]
      },
      "properties": {
        "name": "Morris Park",
        "project": "Penn Station Access (MTA Metro-North)",
        "status": "under construction",
        "line": "New Haven Line (via Amtrak Hell Gate Line)",
        "borough": "Bronx",
        "neighborhood": "Morris Park, Bronx",
        "source_note": "Coords from station Wikipedia pages; station set from MTA project page",
        "created_at_utc": "2025-10-20T23:43:53Z",
        "crs_note": "EPSG:4326 (WGS84 lon,lat)"
      }
    },
    {
      "type": "Feature",
      "id": "psa_station_3",
      "geometry": {
        "type": "Point",
        "coordinates": [
          -73.86251416924942,
          40.841948699239
        ]
      },
      "properties": {
        "name": "Parkchester/Van Nest",
        "project": "Penn Station Access (MTA Metro-North)",
        "status": "under construction",
        "line": "New Haven Line (via Amtrak Hell Gate Line)",
        "borough": "Bronx",
        "neighborhood": "Van Nest / Parkchester, Bronx",
        "source_note": "Coords from station Wikipedia pages; station set from MTA project page",
        "created_at_utc": "2025-10-20T23:43:53Z",
        "crs_note": "EPSG:4326 (WGS84 lon,lat)"
      }
    },
    {
      "type": "Feature",
      "id": "psa_station_4",
      "geometry": {
        "type": "Point",
        "coordinates": [
          -73.88921072806667,
          40.82040811840337
        ]
      },
      "properties": {
        "name": "Hunts Point",
        "project": "Penn Station Access (MTA Metro-North)",
        "status": "under construction",
        "line": "New Haven Line (via Amtrak Hell Gate Line)",
        "borough": "Bronx",
        "neighborhood": "Hunts Point, Bronx",
        "source_note": "Coords from station Wikipedia pages; station set from MTA project page",
        "created_at_utc": "2025-10-20T23:43:53Z",
        "crs_note": "EPSG:4326 (WGS84 lon,lat)"
      }
    }
  ]
}
